genie_flow_invoker/invoker/docproc/__init__.py
genie_flow_invoker/invoker/docproc/backoff_caller.py
genie_flow_invoker/invoker/docproc/codec.py
genie_flow_invoker/invoker/docproc/init_docproc.py
genie_flow_invoker/invoker/docproc/parse.py
genie_flow_invoker/invoker/docproc/chunk/__init__.py
genie_flow_invoker/invoker/docproc/chunk/lexical_density.py
genie_flow_invoker/invoker/docproc/chunk/splitter.py
genie_flow_invoker/invoker/docproc/chunk/transcript.py
genie_flow_invoker/invoker/docproc/chunk/word_splitter.py
genie_flow_invoker/invoker/docproc/clean/__init__.py
genie_flow_invoker/invoker/docproc/clean/cleaner.py
genie_flow_invoker/invoker/docproc/embed/__init__.py
genie_flow_invoker/invoker/docproc/embed/manager.py
genie_flow_invoker/invoker/docproc/model/__init__.py
genie_flow_invoker/invoker/docproc/model/vectorizer.py
genie_flow_invoker/invoker/docproc/similarity_search/__init__.py
genie_flow_invoker/invoker/docproc/similarity_search/db.py
genie_flow_invoker/invoker/docproc/similarity_search/search.py
genie_flow_invoker_docproc-0.7.0a1.dist-info/licenses/NOTICES
genie_flow_invoker_docproc-0.7.0a1.dist-info/METADATA
genie_flow_invoker_docproc-0.7.0a1.dist-info/WHEEL
genie_flow_invoker_docproc-0.7.0a1.dist-info/entry_points.txt
genie_flow_invoker_docproc-0.7.0a1.dist-info/top_level.txt
genie_flow_invoker_docproc-0.7.0a1.dist-info/RECORD
