Metadata-Version: 2.4
Name: genie_flow_invoker_docproc
Version: 0.7.0a1
Summary: Genie Flow Invoker Document Process
Maintainer-email: Willem van Asperen <willem.van.asperen@paconsulting.com>
License-Expression: Apache-2.0
Classifier: Development Status :: 5 - Production/Stable
Classifier: Intended Audience :: Developers
Classifier: Programming Language :: Python :: 3
Classifier: Programming Language :: Python :: 3.11
Classifier: Programming Language :: Python :: 3.12
Classifier: Operating System :: OS Independent
Classifier: Framework :: Celery
Classifier: Framework :: FastAPI
Classifier: Framework :: Pydantic
Classifier: Topic :: Communications :: Chat
Classifier: Topic :: Software Development :: Libraries :: Application Frameworks
Classifier: Topic :: Scientific/Engineering :: Artificial Intelligence
Classifier: Typing :: Typed
Requires-Python: >=3.11.0
License-File: NOTICES
Requires-Dist: loguru~=0.7
Requires-Dist: genie-flow-invoker
Requires-Dist: pydantic~=2.11
Requires-Dist: backoff~=2.2
Requires-Dist: tika~=2.6
Requires-Dist: nltk~=3.9
Requires-Dist: numpy~=2.1
Requires-Dist: sortedcontainers~=2.4
Requires-Dist: webvtt-py~=0.5
Provides-Extra: test
Requires-Dist: pytest; extra == "test"
Requires-Dist: pytest-docker; extra == "test"
Dynamic: license-file
